yacrc/__init__.py
yacrc/yacrc.py
yacrc-0.0.1.dist-info/LICENSE
yacrc-0.0.1.dist-info/METADATA
yacrc-0.0.1.dist-info/WHEEL
yacrc-0.0.1.dist-info/top_level.txt
yacrc-0.0.1.dist-info/RECORD
