Metadata-Version: 2.1
Name: yacrc
Version: 0.0.1
Summary: Yet-Another CRC Calculator
Author-email: Marko Gulin <marko@gulin.fr>
License: MIT License
Project-URL: Homepage, https://github.com/marko-gulin/yacrc
Project-URL: Issues, https://github.com/marko-gulin/yacrc
Keywords: CRC,checksum,error detection
Classifier: Programming Language :: Python :: 3
Classifier: License :: OSI Approved :: MIT License
Classifier: Operating System :: OS Independent
Requires-Python: >=3.7
License-File: LICENSE
